art_resampling/__init__.py
art_resampling/dataset.py
art_resampling/metrics.py
art_resampling-0.1.2.dist-info/licenses/LICENSE
art_resampling-0.1.2.dist-info/METADATA
art_resampling-0.1.2.dist-info/WHEEL
art_resampling-0.1.2.dist-info/RECORD
