Metadata-Version: 2.4
Name: art-resampling
Version: 0.1.2
Summary: ART: Adaptive Resampling-based Training for Imbalanced Classification in PyTorch
License-File: LICENSE
Author: Arjun Basandrai
Author-email: arjunbasandrai2004@gmail.com
Requires-Python: >=3.11,<3.15
Classifier: Programming Language :: Python :: 3
Classifier: Programming Language :: Python :: 3.11
Classifier: Programming Language :: Python :: 3.12
Classifier: Programming Language :: Python :: 3.13
Classifier: Programming Language :: Python :: 3.14
Requires-Dist: numpy (>=1.26,<3)
Requires-Dist: scikit-learn (>=1.3,<2)
Requires-Dist: torch (>=2.10.0,<3.0.0)
